LICENSE
MANIFEST.in
setup.py
django_representatives.egg-info/PKG-INFO
django_representatives.egg-info/SOURCES.txt
django_representatives.egg-info/dependency_links.txt
django_representatives.egg-info/entry_points.txt
django_representatives.egg-info/requires.txt
django_representatives.egg-info/top_level.txt
representatives/__init__.py
representatives/admin.py
representatives/api.py
representatives/models.py
representatives/serializers.py
representatives/contrib/__init__.py
representatives/contrib/francedata/__init__.py
representatives/contrib/francedata/import_representatives.py
representatives/contrib/francedata/variants.py
representatives/contrib/francedata/tests/representatives_expected.json
representatives/contrib/francedata/tests/representatives_input.json
representatives/contrib/francedata/tests/test_francedata_import_representatives.py
representatives/contrib/parltrack/__init__.py
representatives/contrib/parltrack/import_representatives.py
representatives/contrib/parltrack/tests/representatives_expected.json
representatives/contrib/parltrack/tests/representatives_fixture.json
representatives/contrib/parltrack/tests/test_import_representatives.py
representatives/fixtures/country_initial_data.json
representatives/fixtures/representatives_test.json
representatives/management/__init__.py
representatives/management/remove_command.py
representatives/management/commands/__init__.py
representatives/management/commands/remove_constituencies_without_mandate.py
representatives/management/commands/remove_countries_without_constituency.py
representatives/management/commands/remove_groups_without_mandate.py
representatives/migrations/0001_initial.py
representatives/migrations/0002_fixtures.py
representatives/migrations/0003_auto_20150702_1827.py
representatives/migrations/0004_auto_20150709_1601.py
representatives/migrations/0005_auto_20151212_2251.py
representatives/migrations/0006_auto_20151213_0139.py
representatives/migrations/0007_auto_20151213_0156.py
representatives/migrations/0008_constituency_country.py
representatives/migrations/0009_order_mandates_by_end_date_descendant.py
representatives/migrations/0010_index_group_kind_and_abbreviation.py
representatives/migrations/0011_auto_20151226_1938.py
