Metadata-Version: 1.1
Name: django-representatives
Version: 0.0.35
Summary: Base app for government representative
Home-page: http://github.com/political-memory/django-representatives
Author: Laurent Peuch, Olivier Le Thanh Duong, Yohan Boniface, Arnaud Fabre, James Pic, Nicolas Joyard
Author-email: webmaster@memopol.org
License: GPLv3
Keywords: django government parliament
Platform: UNKNOWN
Classifier: Development Status :: 4 - Beta
Classifier: Environment :: Web Environment
Classifier: Framework :: Django
Classifier: Intended Audience :: Developers
Classifier: License :: OSI Approved :: GNU General Public License v3 or later (GPLv3+)
Classifier: Operating System :: OS Independent
Classifier: Programming Language :: Python :: 2
Classifier: Topic :: Software Development :: Libraries :: Python Modules
